odoo8_addon_l10n_it_account_tax_kind-8.0.2.0.0-nspkg.pth
odoo_addons/l10n_it_account_tax_kind/README.rst
odoo_addons/l10n_it_account_tax_kind/__init__.py
odoo_addons/l10n_it_account_tax_kind/__openerp__.py
odoo_addons/l10n_it_account_tax_kind/data/account.tax.kind.csv
odoo_addons/l10n_it_account_tax_kind/i18n/it.po
odoo_addons/l10n_it_account_tax_kind/i18n/l10n_it_account_tax_kind.pot
odoo_addons/l10n_it_account_tax_kind/i18n/sl.po
odoo_addons/l10n_it_account_tax_kind/model/__init__.py
odoo_addons/l10n_it_account_tax_kind/model/account.py
odoo_addons/l10n_it_account_tax_kind/model/account_tax_kind.py
odoo_addons/l10n_it_account_tax_kind/security/ir.model.access.csv
odoo_addons/l10n_it_account_tax_kind/static/description/icon.png
odoo_addons/l10n_it_account_tax_kind/view/account_tax_kind_view.xml
odoo_addons/l10n_it_account_tax_kind/view/account_tax_view.xml
odoo8_addon_l10n_it_account_tax_kind-8.0.2.0.0.dist-info/METADATA
odoo8_addon_l10n_it_account_tax_kind-8.0.2.0.0.dist-info/WHEEL
odoo8_addon_l10n_it_account_tax_kind-8.0.2.0.0.dist-info/namespace_packages.txt
odoo8_addon_l10n_it_account_tax_kind-8.0.2.0.0.dist-info/top_level.txt
odoo8_addon_l10n_it_account_tax_kind-8.0.2.0.0.dist-info/RECORD
