Metadata-Version: 2.1
Name: odoo8-addon-l10n-it-account-tax-kind
Version: 8.0.2.0.0
Summary: Italian Localisation - Natura delle aliquote IVA
Home-page: https://www.odoo-italia.net/
Author: Odoo Community Association (OCA), Apulia Software s.r.l
Author-email: support@odoo-community.org
License: AGPL-3
Platform: UNKNOWN
Classifier: Programming Language :: Python
Classifier: Framework :: Odoo
Classifier: License :: OSI Approved :: GNU Affero General Public License v3
Requires-Python: ~=2.7
Requires-Dist: odoo (<9.0a,>=8.0a)
